terranproduction/__init__.py
terranproduction/app.py
terranproduction/database.py
terranproduction/replay.py
terranproduction/util.py
terranproduction/static/images/allin_official.png
terranproduction/static/styles/main.css
terranproduction/templates/analysis.html.j2
terranproduction/templates/index.html.j2
terranproduction-0.0.3.dist-info/METADATA
terranproduction-0.0.3.dist-info/RECORD
terranproduction-0.0.3.dist-info/WHEEL
terranproduction-0.0.3.dist-info/top_level.txt
